{
"meta":{"test_sets":[],"test_metrics":[],"learn_metrics":[{"best_value":"Min","name":"Logloss"}],"launch_mode":"Train","parameters":"","iteration_count":200,"learn_sets":["learn"],"name":"experiment"},
"iterations":[
{"learn":[0.6770840883],"iteration":0,"passed_time":0.04772661439,"remaining_time":9.497596263},
{"learn":[0.6682341099],"iteration":1,"passed_time":0.04884490709,"remaining_time":4.835645802},
{"learn":[0.6625704169],"iteration":2,"passed_time":0.05084378292,"remaining_time":3.338741745},
{"learn":[0.6583297253],"iteration":3,"passed_time":0.05174994847,"remaining_time":2.535747475},
{"learn":[0.6565328836],"iteration":4,"passed_time":0.05271041109,"remaining_time":2.055706032},
{"learn":[0.6543521285],"iteration":5,"passed_time":0.05400720258,"remaining_time":1.746232883},
{"learn":[0.6528309584],"iteration":6,"passed_time":0.05529627338,"remaining_time":1.524597252},
{"learn":[0.6520616412],"iteration":7,"passed_time":0.05741747766,"remaining_time":1.378019464},
{"learn":[0.6514890194],"iteration":8,"passed_time":0.05845696816,"remaining_time":1.240586769},
{"learn":[0.6510803699],"iteration":9,"passed_time":0.05938305621,"remaining_time":1.128278068},
{"learn":[0.6507467031],"iteration":10,"passed_time":0.06094946819,"remaining_time":1.047222681},
{"learn":[0.6498070955],"iteration":11,"passed_time":0.06370938373,"remaining_time":0.9981136784},
{"learn":[0.6493747234],"iteration":12,"passed_time":0.06482686491,"remaining_time":0.9325095184},
{"learn":[0.648927927],"iteration":13,"passed_time":0.06578329777,"remaining_time":0.8739780989},
{"learn":[0.6486544609],"iteration":14,"passed_time":0.06682526257,"remaining_time":0.8241782384},
{"learn":[0.648157239],"iteration":15,"passed_time":0.06790406914,"remaining_time":0.7808967951},
{"learn":[0.6476626396],"iteration":16,"passed_time":0.07010011376,"remaining_time":0.754607107},
{"learn":[0.6473038197],"iteration":17,"passed_time":0.07232895874,"remaining_time":0.7313261384},
{"learn":[0.6472052336],"iteration":18,"passed_time":0.07333627578,"remaining_time":0.6986245219},
{"learn":[0.6470678449],"iteration":19,"passed_time":0.07543232152,"remaining_time":0.6788908937},
{"learn":[0.646886766],"iteration":20,"passed_time":0.07702094118,"remaining_time":0.656511832},
{"learn":[0.6466305852],"iteration":21,"passed_time":0.07939638696,"remaining_time":0.642388949},
{"learn":[0.6462023258],"iteration":22,"passed_time":0.08105381492,"remaining_time":0.623761967},
{"learn":[0.6460478306],"iteration":23,"passed_time":0.08235823011,"remaining_time":0.6039603542},
{"learn":[0.645740509],"iteration":24,"passed_time":0.08378746973,"remaining_time":0.5865122881},
{"learn":[0.6454162598],"iteration":25,"passed_time":0.08507289615,"remaining_time":0.5693339973},
{"learn":[0.6450964212],"iteration":26,"passed_time":0.08675666663,"remaining_time":0.5558853084},
{"learn":[0.644259572],"iteration":27,"passed_time":0.08912470823,"remaining_time":0.5474803506},
{"learn":[0.6442342997],"iteration":28,"passed_time":0.09035294717,"remaining_time":0.5327708264},
{"learn":[0.6436018944],"iteration":29,"passed_time":0.09159189421,"remaining_time":0.5190207338},
{"learn":[0.6434136629],"iteration":30,"passed_time":0.09309219141,"remaining_time":0.5075025919},
{"learn":[0.6430621147],"iteration":31,"passed_time":0.0945117226,"remaining_time":0.4961865437},
{"learn":[0.6425991058],"iteration":32,"passed_time":0.09605562299,"remaining_time":0.4860996679},
{"learn":[0.6420676112],"iteration":33,"passed_time":0.09783075636,"remaining_time":0.477644281},
{"learn":[0.6417753696],"iteration":34,"passed_time":0.09918862931,"remaining_time":0.4676035382},
{"learn":[0.6414084435],"iteration":35,"passed_time":0.1003689779,"remaining_time":0.457236455},
{"learn":[0.6411419511],"iteration":36,"passed_time":0.1022369381,"remaining_time":0.4503951599},
{"learn":[0.6410072446],"iteration":37,"passed_time":0.1037041644,"remaining_time":0.4421072271},
{"learn":[0.640635252],"iteration":38,"passed_time":0.1048112064,"remaining_time":0.43268216},
{"learn":[0.6402485371],"iteration":39,"passed_time":0.1062736244,"remaining_time":0.4250944975},
{"learn":[0.6398639083],"iteration":40,"passed_time":0.1075158601,"remaining_time":0.4169517503},
{"learn":[0.6390867829],"iteration":41,"passed_time":0.108954331,"remaining_time":0.4098758165},
{"learn":[0.6388570666],"iteration":42,"passed_time":0.1101258816,"remaining_time":0.4020875213},
{"learn":[0.6383078098],"iteration":43,"passed_time":0.1114422439,"remaining_time":0.3951134101},
{"learn":[0.6379601955],"iteration":44,"passed_time":0.11347705,"remaining_time":0.3908653946},
{"learn":[0.637270391],"iteration":45,"passed_time":0.1152406593,"remaining_time":0.3858056854},
{"learn":[0.6371921301],"iteration":46,"passed_time":0.1164752707,"remaining_time":0.379164179},
{"learn":[0.6369301081],"iteration":47,"passed_time":0.1176154038,"remaining_time":0.3724487786},
{"learn":[0.6364975572],"iteration":48,"passed_time":0.1203876304,"remaining_time":0.3709904529},
{"learn":[0.636315763],"iteration":49,"passed_time":0.1220600099,"remaining_time":0.3661800298},
{"learn":[0.6360293627],"iteration":50,"passed_time":0.1231834203,"remaining_time":0.3598888163},
{"learn":[0.6358482838],"iteration":51,"passed_time":0.1241387484,"remaining_time":0.3533179763},
{"learn":[0.6354707479],"iteration":52,"passed_time":0.125348233,"remaining_time":0.347663967},
{"learn":[0.6353313923],"iteration":53,"passed_time":0.1264366976,"remaining_time":0.3418473675},
{"learn":[0.6351907253],"iteration":54,"passed_time":0.127550418,"remaining_time":0.3362692837},
{"learn":[0.6347424984],"iteration":55,"passed_time":0.1288181333,"remaining_time":0.3312466286},
{"learn":[0.6344487071],"iteration":56,"passed_time":0.1301093212,"remaining_time":0.3264146128},
{"learn":[0.6340733171],"iteration":57,"passed_time":0.1311600513,"remaining_time":0.3211159877},
{"learn":[0.6339025497],"iteration":58,"passed_time":0.1322223945,"remaining_time":0.3159891123},
{"learn":[0.6336705685],"iteration":59,"passed_time":0.1332760293,"remaining_time":0.3109774016},
{"learn":[0.6333909035],"iteration":60,"passed_time":0.1343465965,"remaining_time":0.3061340478},
{"learn":[0.6332086325],"iteration":61,"passed_time":0.1358949354,"remaining_time":0.3024758238},
{"learn":[0.6331754923],"iteration":62,"passed_time":0.1371456445,"remaining_time":0.2982373539},
{"learn":[0.6329888105],"iteration":63,"passed_time":0.1382566607,"remaining_time":0.293795404},
{"learn":[0.6325850487],"iteration":64,"passed_time":0.1411840996,"remaining_time":0.2932285145},
{"learn":[0.6320815086],"iteration":65,"passed_time":0.1436052898,"remaining_time":0.2915622551},
{"learn":[0.6315348148],"iteration":66,"passed_time":0.1447473647,"remaining_time":0.2873343211},
{"learn":[0.6306292415],"iteration":67,"passed_time":0.1462839583,"remaining_time":0.2839629778},
{"learn":[0.6302859783],"iteration":68,"passed_time":0.1475699628,"remaining_time":0.2801690598},
{"learn":[0.6298412681],"iteration":69,"passed_time":0.1486725936,"remaining_time":0.2761062452},
{"learn":[0.6295495629],"iteration":70,"passed_time":0.1497478217,"remaining_time":0.2720770282},
{"learn":[0.6292062402],"iteration":71,"passed_time":0.1513212457,"remaining_time":0.2690155479},
{"learn":[0.6290560365],"iteration":72,"passed_time":0.1526777132,"remaining_time":0.2656173915},
{"learn":[0.6287388802],"iteration":73,"passed_time":0.1539278637,"remaining_time":0.2620933895},
{"learn":[0.62830621],"iteration":74,"passed_time":0.155165458,"remaining_time":0.2586090966},
{"learn":[0.6279530525],"iteration":75,"passed_time":0.1571004379,"remaining_time":0.2563217671},
{"learn":[0.6277374029],"iteration":76,"passed_time":0.1581704465,"remaining_time":0.2526618821},
{"learn":[0.6275260448],"iteration":77,"passed_time":0.1593125641,"remaining_time":0.24918119},
{"learn":[0.6273479462],"iteration":78,"passed_time":0.1616431442,"remaining_time":0.2475800056},
{"learn":[0.6268888712],"iteration":79,"passed_time":0.1632304822,"remaining_time":0.2448457233},
{"learn":[0.6264508367],"iteration":80,"passed_time":0.1645662548,"remaining_time":0.2417701768},
{"learn":[0.6259699464],"iteration":81,"passed_time":0.1655512507,"remaining_time":0.2382322876},
{"learn":[0.625813365],"iteration":82,"passed_time":0.1667879637,"remaining_time":0.2351107439},
{"learn":[0.6255966425],"iteration":83,"passed_time":0.1681127824,"remaining_time":0.2321557472},
{"learn":[0.6253224611],"iteration":84,"passed_time":0.1697492872,"remaining_time":0.2296608004},
{"learn":[0.625053823],"iteration":85,"passed_time":0.1708507567,"remaining_time":0.2264765845},
{"learn":[0.624600172],"iteration":86,"passed_time":0.1718286213,"remaining_time":0.2231797035},
{"learn":[0.6244639158],"iteration":87,"passed_time":0.1734180854,"remaining_time":0.2207139269},
{"learn":[0.6242156029],"iteration":88,"passed_time":0.1748572921,"remaining_time":0.218080443},
{"learn":[0.6240175366],"iteration":89,"passed_time":0.1762398067,"remaining_time":0.2154042081},
{"learn":[0.623708725],"iteration":90,"passed_time":0.1774231718,"remaining_time":0.2125178651},
{"learn":[0.623577714],"iteration":91,"passed_time":0.1784498281,"remaining_time":0.2094845808},
{"learn":[0.6233494282],"iteration":92,"passed_time":0.1799043239,"remaining_time":0.2069866952},
{"learn":[0.6229817271],"iteration":93,"passed_time":0.1815300145,"remaining_time":0.2047040589},
{"learn":[0.6228763461],"iteration":94,"passed_time":0.1825808365,"remaining_time":0.2017998719},
{"learn":[0.6228175163],"iteration":95,"passed_time":0.1835727095,"remaining_time":0.1988704353},
{"learn":[0.622579217],"iteration":96,"passed_time":0.1846380107,"remaining_time":0.1960589186},
{"learn":[0.6224428415],"iteration":97,"passed_time":0.1857478966,"remaining_time":0.1933294434},
{"learn":[0.6222356558],"iteration":98,"passed_time":0.1872599339,"remaining_time":0.1910429629},
{"learn":[0.621889174],"iteration":99,"passed_time":0.1887777366,"remaining_time":0.1887777366},
{"learn":[0.6217194796],"iteration":100,"passed_time":0.1904270148,"remaining_time":0.1866561828},
{"learn":[0.6213849187],"iteration":101,"passed_time":0.1915574466,"remaining_time":0.1840453898},
{"learn":[0.621091187],"iteration":102,"passed_time":0.1927935394,"remaining_time":0.1815628478},
{"learn":[0.6207914352],"iteration":103,"passed_time":0.1939931309,"remaining_time":0.1790705824},
{"learn":[0.6206140518],"iteration":104,"passed_time":0.1960846435,"remaining_time":0.1774099156},
{"learn":[0.6204029918],"iteration":105,"passed_time":0.1978517684,"remaining_time":0.175453455},
{"learn":[0.6199778318],"iteration":106,"passed_time":0.1995617401,"remaining_time":0.1734508583},
{"learn":[0.619602561],"iteration":107,"passed_time":0.2010818241,"remaining_time":0.1712919242},
{"learn":[0.6192392111],"iteration":108,"passed_time":0.2022803441,"remaining_time":0.1688762506},
{"learn":[0.618894577],"iteration":109,"passed_time":0.2036255769,"remaining_time":0.1666027447},
{"learn":[0.618845582],"iteration":110,"passed_time":0.2045969558,"remaining_time":0.1640462078},
{"learn":[0.6186469793],"iteration":111,"passed_time":0.2059624078,"remaining_time":0.1618276061},
{"learn":[0.6185919046],"iteration":112,"passed_time":0.2073739066,"remaining_time":0.1596595564},
{"learn":[0.6184462309],"iteration":113,"passed_time":0.2086198463,"remaining_time":0.157379884},
{"learn":[0.6182872057],"iteration":114,"passed_time":0.2098825788,"remaining_time":0.1551306017},
{"learn":[0.6182364225],"iteration":115,"passed_time":0.2111168714,"remaining_time":0.1528777345},
{"learn":[0.6180684566],"iteration":116,"passed_time":0.2126641511,"remaining_time":0.1508643123},
{"learn":[0.6179895401],"iteration":117,"passed_time":0.2142960467,"remaining_time":0.1489175918},
{"learn":[0.6179229021],"iteration":118,"passed_time":0.21564978,"remaining_time":0.146786825},
{"learn":[0.617863059],"iteration":119,"passed_time":0.2169005279,"remaining_time":0.1446003519},
{"learn":[0.6175970435],"iteration":120,"passed_time":0.2181571511,"remaining_time":0.1424331813},
{"learn":[0.6172544956],"iteration":121,"passed_time":0.2198234717,"remaining_time":0.1405428754},
{"learn":[0.6167134643],"iteration":122,"passed_time":0.2216609695,"remaining_time":0.1387633711},
{"learn":[0.6164118648],"iteration":123,"passed_time":0.2230245676,"remaining_time":0.1366924769},
{"learn":[0.616037488],"iteration":124,"passed_time":0.2241744059,"remaining_time":0.1345046436},
{"learn":[0.6159133315],"iteration":125,"passed_time":0.226013828,"remaining_time":0.1327382799},
{"learn":[0.6153334975],"iteration":126,"passed_time":0.2273127404,"remaining_time":0.1306600791},
{"learn":[0.6152123213],"iteration":127,"passed_time":0.2290246003,"remaining_time":0.1288263377},
{"learn":[0.6149811149],"iteration":128,"passed_time":0.2302115406,"remaining_time":0.1267055766},
{"learn":[0.614782393],"iteration":129,"passed_time":0.2317613822,"remaining_time":0.1247945904},
{"learn":[0.6144453883],"iteration":130,"passed_time":0.2334545623,"remaining_time":0.1229646168},
{"learn":[0.6142488122],"iteration":131,"passed_time":0.2348280939,"remaining_time":0.1209720484},
{"learn":[0.6139316559],"iteration":132,"passed_time":0.2359073088,"remaining_time":0.118840524},
{"learn":[0.6132433414],"iteration":133,"passed_time":0.2371005033,"remaining_time":0.1167808449},
{"learn":[0.6132023335],"iteration":134,"passed_time":0.2387347013,"remaining_time":0.1149463377},
{"learn":[0.6129938364],"iteration":135,"passed_time":0.2405493525,"remaining_time":0.1131996953},
{"learn":[0.6128062606],"iteration":136,"passed_time":0.2417489278,"remaining_time":0.111169215},
{"learn":[0.6126735806],"iteration":137,"passed_time":0.2429792566,"remaining_time":0.1091645936},
{"learn":[0.6126422882],"iteration":138,"passed_time":0.2440468161,"remaining_time":0.1070996819},
{"learn":[0.6123641729],"iteration":139,"passed_time":0.24561321,"remaining_time":0.1052628043},
{"learn":[0.6123164892],"iteration":140,"passed_time":0.2470082419,"remaining_time":0.1033580587},
{"learn":[0.6121970415],"iteration":141,"passed_time":0.2485966508,"remaining_time":0.1015394771},
{"learn":[0.6119849682],"iteration":142,"passed_time":0.2498158408,"remaining_time":0.09957694355},
{"learn":[0.6117588282],"iteration":143,"passed_time":0.2510506572,"remaining_time":0.09763081115},
{"learn":[0.6115729809],"iteration":144,"passed_time":0.252891467,"remaining_time":0.09592434954},
{"learn":[0.6110498905],"iteration":145,"passed_time":0.2545513059,"remaining_time":0.09414911313},
{"learn":[0.6109066606],"iteration":146,"passed_time":0.2557459759,"remaining_time":0.09220773282},
{"learn":[0.610753119],"iteration":147,"passed_time":0.2568118422,"remaining_time":0.09023118782},
{"learn":[0.6105937362],"iteration":148,"passed_time":0.2582598246,"remaining_time":0.08839765809},
{"learn":[0.6101549864],"iteration":149,"passed_time":0.2593863197,"remaining_time":0.08646210658},
{"learn":[0.6098005772],"iteration":150,"passed_time":0.2605905495,"remaining_time":0.08456249619},
{"learn":[0.609713912],"iteration":151,"passed_time":0.2617887608,"remaining_time":0.08267013499},
{"learn":[0.6096068621],"iteration":152,"passed_time":0.2627932314,"remaining_time":0.08072733252},
{"learn":[0.6095548272],"iteration":153,"passed_time":0.2638802669,"remaining_time":0.07882137843},
{"learn":[0.6095203161],"iteration":154,"passed_time":0.2649036254,"remaining_time":0.07690750415},
{"learn":[0.609490335],"iteration":155,"passed_time":0.2659059906,"remaining_time":0.07499912555},
{"learn":[0.6094589233],"iteration":156,"passed_time":0.2670695477,"remaining_time":0.07314643662},
{"learn":[0.6092059016],"iteration":157,"passed_time":0.2681546963,"remaining_time":0.07128162814},
{"learn":[0.6088490486],"iteration":158,"passed_time":0.2691244196,"remaining_time":0.06939686291},
{"learn":[0.6086033583],"iteration":159,"passed_time":0.270196382,"remaining_time":0.06754909549},
{"learn":[0.6085368991],"iteration":160,"passed_time":0.2713510066,"remaining_time":0.06573098917},
{"learn":[0.6082591414],"iteration":161,"passed_time":0.272442033,"remaining_time":0.0639061559},
{"learn":[0.608093679],"iteration":162,"passed_time":0.2742519871,"remaining_time":0.06225351855},
{"learn":[0.6076849103],"iteration":163,"passed_time":0.2753733274,"remaining_time":0.06044780357},
{"learn":[0.6075561047],"iteration":164,"passed_time":0.2764841432,"remaining_time":0.05864815158},
{"learn":[0.6074015498],"iteration":165,"passed_time":0.2776785985,"remaining_time":0.05687392982},
{"learn":[0.607100606],"iteration":166,"passed_time":0.2787055264,"remaining_time":0.05507354714},
{"learn":[0.6069660187],"iteration":167,"passed_time":0.2799205264,"remaining_time":0.0533181955},
{"learn":[0.6068253517],"iteration":168,"passed_time":0.2811986653,"remaining_time":0.05158082027},
{"learn":[0.6066560745],"iteration":169,"passed_time":0.2828411895,"remaining_time":0.0499131511},
{"learn":[0.6063261032],"iteration":170,"passed_time":0.2838127043,"remaining_time":0.04813197909},
{"learn":[0.6060847044],"iteration":171,"passed_time":0.2847263681,"remaining_time":0.04635080411},
{"learn":[0.6059465408],"iteration":172,"passed_time":0.2856017763,"remaining_time":0.04457368763},
{"learn":[0.6057880521],"iteration":173,"passed_time":0.2867867728,"remaining_time":0.04285319594},
{"learn":[0.6055559516],"iteration":174,"passed_time":0.2880344558,"remaining_time":0.0411477794},
{"learn":[0.6055554152],"iteration":175,"passed_time":0.2893646749,"remaining_time":0.0394588193},
{"learn":[0.6054003835],"iteration":176,"passed_time":0.2905615822,"remaining_time":0.03775658978},
{"learn":[0.6052882671],"iteration":177,"passed_time":0.2917312292,"remaining_time":0.03605666878},
{"learn":[0.6052466035],"iteration":178,"passed_time":0.2928885166,"remaining_time":0.03436122262},
{"learn":[0.6047950983],"iteration":179,"passed_time":0.2939607936,"remaining_time":0.0326623104},
{"learn":[0.6045782566],"iteration":180,"passed_time":0.2952933162,"remaining_time":0.03099764093},
{"learn":[0.604521513],"iteration":181,"passed_time":0.2966280284,"remaining_time":0.02933683797},
{"learn":[0.6042987108],"iteration":182,"passed_time":0.2976841853,"remaining_time":0.02765372213},
{"learn":[0.6041755676],"iteration":183,"passed_time":0.2987994563,"remaining_time":0.02598256142},
{"learn":[0.6039629579],"iteration":184,"passed_time":0.3000173632,"remaining_time":0.02432573215},
{"learn":[0.6036933661],"iteration":185,"passed_time":0.3012486076,"remaining_time":0.02267462638},
{"learn":[0.6034830809],"iteration":186,"passed_time":0.3025865102,"remaining_time":0.02103542584},
{"learn":[0.6031218767],"iteration":187,"passed_time":0.3037457362,"remaining_time":0.01938802572},
{"learn":[0.6030002832],"iteration":188,"passed_time":0.3048466535,"remaining_time":0.01774239782},
{"learn":[0.6028815508],"iteration":189,"passed_time":0.3060264282,"remaining_time":0.01610665412},
{"learn":[0.6026542187],"iteration":190,"passed_time":0.3077327885,"remaining_time":0.01450049789},
{"learn":[0.6025303602],"iteration":191,"passed_time":0.3090416104,"remaining_time":0.01287673377},
{"learn":[0.6024516821],"iteration":192,"passed_time":0.3104308512,"remaining_time":0.01125915004},
{"learn":[0.6023323536],"iteration":193,"passed_time":0.3116270644,"remaining_time":0.009637950445},
{"learn":[0.6020903587],"iteration":194,"passed_time":0.312862111,"remaining_time":0.00802210541},
{"learn":[0.6016592979],"iteration":195,"passed_time":0.3140998388,"remaining_time":0.006410200792},
{"learn":[0.6014738679],"iteration":196,"passed_time":0.3159222185,"remaining_time":0.004810998251},
{"learn":[0.6013246179],"iteration":197,"passed_time":0.31734718,"remaining_time":0.003205527071},
{"learn":[0.6006550789],"iteration":198,"passed_time":0.3186871518,"remaining_time":0.001601442974},
{"learn":[0.6002067327],"iteration":199,"passed_time":0.3202083182,"remaining_time":0}
]}